{
   "d":{
      "results":[
         {
            "OfferCode":"50038473",
            "Type":"H",
            "EFLType":"BR",
            "EFLLevel":1000,
            "EFLPrice":"10.2000000",
            "EFLString":""
         },
         {
            "OfferCode":"50038473",
            "Type":"H",
            "EFLType":"BR",
            "EFLLevel":2000,
            "EFLPrice":"9.7000000",
            "EFLString":""
         },
         {
            "OfferCode":"50038473",
            "Type":"H",
            "EFLType":"BR",
            "EFLLevel":500,
            "EFLPrice":"11.0000000",
            "EFLString":""
         },
         {
            "OfferCode":"50038473",
            "Type":"H",
            "EFLType":"BR",
            "EFLLevel":1000,
            "EFLPrice":"10.2000000",
            "EFLString":""
         },
         {
            "OfferCode":"50038473",
            "Type":"H",
            "EFLType":"BR",
            "EFLLevel":2000,
            "EFLPrice":"9.7000000",
            "EFLString":""
         },
         {
            "OfferCode":"50038473",
            "Type":"H",
            "EFLType":"BR",
            "EFLLevel":500,
            "EFLPrice":"11.0000000",
            "EFLString":""
         },
         {
            "OfferCode":"50038473",
            "Type":"H",
            "EFLType":"BR",
            "EFLLevel":1000,
            "EFLPrice":"7.6000000",
            "EFLString":""
         },
         {
            "OfferCode":"50038473",
            "Type":"H",
            "EFLType":"BR",
            "EFLLevel":2000,
            "EFLPrice":"7.1000000",
            "EFLString":""
         },
         {
            "OfferCode":"50038473",
            "Type":"H",
            "EFLType":"BR",
            "EFLLevel":500,
            "EFLPrice":"10.5000000",
            "EFLString":""
         }
      ]
   }
}
